[{"attribute": "licenseURL", "attributeValue_np": "https://creativecommons.org/licenses/by/4.0/"}, {"attribute": "mimeType", "attributeValue_np": "dicom"}, {"attribute": "media-type-IANA-application", "attributeValue_np": "dicom"}, {"attribute": "digitalObjectLocation", "attributeValue_np": "https://b2share.eudat.eu/"}, {"attribute": "MedicalImageModality", "attributeValue_np": "MR"}, {"attribute": "contrastType", "attributeValue_np": "T2-weighted"}, {"attribute": "imageCompressionDetails", "attributeValue_np": "lossless"}, {"attribute": "fileMagnitude", "attributeValue_np": "1E5-2E5"}, {"attribute": "version", "attributeValue_np": "1.0.0"}, {"attribute": "dateCreated", "attributeValue_np": "2023-06-21T00:00:00+00:00"}, {"attribute": "contact", "attributeValue_np": "https://orcid.org/0009-0007-0235-4995"}, {"attribute": "digitalObjectLocation", "attributeValue_np": "https://b2share.eudat.eu/api/files/aeb2c0c5-38dd-4863-ba3a-c075e7a658dd/Phantom_E102_P1_EnIm1.dcm"}]